{"assets":{"5BA6DF7ACEF516F7DAB78587CF30CE20":{"type":"texture","index":414,"assetRequest":{"type":"slide","state":"contents","slide":"65A7F75D-376B-4611-8BEB-E835A6CA23A7"},"url":{"web":"assets/5BA6DF7ACEF516F7DAB78587CF30CE20.svg"},"width":1920,"height":1080},"F9D67537335693395CBA785731CD3476":{"type":"texture","index":419,"assetRequest":{"type":"slide","state":"incoming","slide":"948002CC-1BB1-4EBC-881D-D6127FC04B51"},"url":{"web":"assets/F9D67537335693395CBA785731CD3476.svg"},"width":1920,"height":1080},"404D9F46CAD725E5CB6CF5313B387FE7":{"type":"texture","index":416,"assetRequest":{"type":"slide","state":"contents","slide":"65A7F75D-376B-4611-8BEB-E835A6CA23A7"},"url":{"web":"assets/404D9F46CAD725E5CB6CF5313B387FE7.svg"},"width":1012,"height":577},"F4E2A4BA55073D68C26FB26933B5B581":{"url":{"web":"assets/F4E2A4BA55073D68C26FB26933B5B581.svg"},"height":573.0691528320312,"movie":"regular-show.gif-0.0000-2.5600","width":1008.924621582031,"type":"texture","assetRequest":{"byGlyphStyle":0,"deliveryStyle":0,"chunkIndex":1,"type":"chunk","chunkCount":1,"stageIndex":0,"stageCount":1},"index":417},"FD41AC253A9043B533BAC166837C08A6":{"type":"texture","index":418,"assetRequest":{"type":"slide","state":"outgoing","slide":"65A7F75D-376B-4611-8BEB-E835A6CA23A7"},"url":{"web":"assets/FD41AC253A9043B533BAC166837C08A6.svg"},"width":1920,"height":1080},"regular-show.gif-0.0000-2.5600":{"type":"video","index":0,"assetRequest":{},"url":{"web":"assets/regular-show.gif-0.0000-2.5600.gif","native":"assets/regular-show.gif-0.0000-2.5600.gif"},"width":500,"height":284},"BC73DB09C2BE6F8E1AB988C55A0D508F":{"type":"texture","index":415,"assetRequest":{"type":"slide","state":"contents","slide":"65A7F75D-376B-4611-8BEB-E835A6CA23A7"},"url":{"web":"assets/BC73DB09C2BE6F8E1AB988C55A0D508F.svg"},"width":804,"height":150}},"events":[{"effects":[{"beginTime":0,"baseLayer":{"animations":[],"initialState":{"affineTransform":[1,0,0,1,0,0],"masksToBounds":false,"rotation":0,"scale":1,"position":{"pointX":960,"pointY":658.5218505859375},"width":1008.924621582031,"sublayerTransform":[1,0,0,0,0,1,0,0,0,0,1,0,0,0,0,1],"contentsRect":{"y":0,"x":0,"width":1,"height":1},"opacity":1,"edgeAntialiasingMask":251658240,"height":573.0691528320312,"hidden":false,"anchorPoint":{"pointX":0.5,"pointY":0.5}},"objectID":"02FC3272-4CF6-46E2-9883-36AFEF6E092B","layers":[{"animations":[],"initialState":{"affineTransform":[1,0,0,1,0,0],"masksToBounds":false,"rotation":0,"scale":1,"position":{"pointX":504.4623107910156,"pointY":168.0127258300781},"width":1008.924621582031,"sublayerTransform":[1,0,0,0,0,1,0,0,0,0,1,-0.0003500791246677598,0,0,0,1],"contentsRect":{"y":0,"x":0,"width":1,"height":1},"opacity":1,"edgeAntialiasingMask":251658240,"height":573.0691528320312,"hidden":false,"anchorPoint":{"pointX":0.5,"pointY":0.2931805437437727}},"layers":[{"animations":[{"timeOffset":0,"beginTime":1e-100,"repeatCount":0,"animations":[{"timeOffset":0,"from":{"scalar":true},"beginTime":0,"repeatCount":0,"fillMode":"removed","property":"isPlaying","autoreverses":false,"duration":0.01,"to":{"scalar":true}},{"timeOffset":0,"from":{"scalar":false},"beginTime":0,"repeatCount":0,"fillMode":"removed","property":"hidden","autoreverses":false,"duration":0.01,"to":{"scalar":false}}],"fillMode":"both","autoreverses":false,"duration":0.01}],"layers":[],"initialState":{"affineTransform":[1,0,0,1,0,0],"masksToBounds":false,"rotation":0,"scale":1,"position":{"pointX":504.4623107910156,"pointY":286.5127258300781},"width":1012,"sublayerTransform":[1,0,0,0,0,1,0,0,0,0,1,0,0,0,0,1],"contentsRect":{"y":0,"x":0,"width":1,"height":1},"opacity":1,"edgeAntialiasingMask":0,"height":577,"hidden":false,"anchorPoint":{"pointX":0.5,"pointY":0.5}},"texture":"404D9F46CAD725E5CB6CF5313B387FE7"}]}]},"effects":[{"beginTime":0,"baseLayer":{"animations":[],"initialState":{"affineTransform":[1,0,0,1,0,0],"masksToBounds":false,"rotation":0,"scale":1,"position":{"pointX":960,"pointY":658.5218505859375},"width":1008.924621582031,"sublayerTransform":[1,0,0,0,0,1,0,0,0,0,1,0,0,0,0,1],"contentsRect":{"y":0,"x":0,"width":1,"height":1},"opacity":1,"edgeAntialiasingMask":251658240,"height":573.0691528320312,"hidden":false,"anchorPoint":{"pointX":0.5,"pointY":0.5}},"objectID":"02FC3272-4CF6-46E2-9883-36AFEF6E092B","layers":[{"animations":[],"layers":[],"initialState":{"affineTransform":[1,0,0,1,0,0],"masksToBounds":false,"rotation":0,"scale":1,"position":{"pointX":504.4623107910156,"pointY":286.5127258300781},"width":1012,"sublayerTransform":[1,0,0,0,0,1,0,0,0,0,1,0,0,0,0,1],"contentsRect":{"y":0,"x":0,"width":1,"height":1},"opacity":1,"edgeAntialiasingMask":0,"height":577,"hidden":true,"anchorPoint":{"pointX":0.5,"pointY":0.5}},"texture":"404D9F46CAD725E5CB6CF5313B387FE7"},{"animations":[],"layers":[],"initialState":{"affineTransform":[1,0,0,1,0,0],"masksToBounds":false,"rotation":0,"scale":1,"position":{"pointX":504.4623107910156,"pointY":286.5345764160156},"width":1008.924621582031,"sublayerTransform":[1,0,0,0,0,1,0,0,0,0,1,0,0,0,0,1],"contentsRect":{"y":0,"x":0,"width":1,"height":1},"opacity":1,"edgeAntialiasingMask":251658240,"height":573.0691528320312,"hidden":false,"anchorPoint":{"pointX":0.5,"pointY":0.5}},"texture":"F4E2A4BA55073D68C26FB26933B5B581"}]},"effects":[],"movie":{"volume":1,"isStreaming":false,"isAudioOnly":false,"endTime":2.559999942779541,"startTime":0,"asset":"regular-show.gif-0.0000-2.5600","loopMode":"looping"},"duration":0,"type":"buildIn","name":"renderMovie","objectID":"02FC3272-4CF6-46E2-9883-36AFEF6E092B"}],"duration":0.01,"type":"buildIn","name":"apple:movie-start","objectID":"02FC3272-4CF6-46E2-9883-36AFEF6E092B"}],"automaticPlay":false,"hyperlinks":[],"accessibility":[{"text":"ECMAScript","targetRectangle":{"y":134.9503479003906,"x":553.920015258789,"width":812.16,"height":189.35888671875}}],"baseLayer":{"animations":[],"initialState":{"affineTransform":[1,0,0,1,0,0],"masksToBounds":false,"rotation":0,"scale":1,"position":{"pointX":960,"pointY":540},"width":1920,"sublayerTransform":[1,0,0,0,0,1,0,0,0,0,1,0,0,0,0,1],"contentsRect":{"y":0,"x":0,"width":1,"height":1},"opacity":1,"edgeAntialiasingMask":251658240,"height":1080,"hidden":false,"anchorPoint":{"pointX":0.5,"pointY":0.5}},"layers":[{"animations":[],"initialState":{"affineTransform":[1,0,0,1,0,0],"masksToBounds":false,"rotation":0,"scale":1,"position":{"pointX":960,"pointY":540},"width":1920,"sublayerTransform":[1,0,0,0,0,1,0,0,0,0,1,0,0,0,0,1],"contentsRect":{"y":0,"x":0,"width":1,"height":1},"opacity":1,"edgeAntialiasingMask":251658240,"height":1080,"hidden":false,"anchorPoint":{"pointX":0.5,"pointY":0.5}},"layers":[{"animations":[],"initialState":{"affineTransform":[1,0,0,1,0,0],"masksToBounds":false,"rotation":0,"scale":1,"position":{"pointX":960,"pointY":540},"width":1920,"sublayerTransform":[1,0,0,0,0,1,0,0,0,0,1,0,0,0,0,1],"contentsRect":{"y":0,"x":0,"width":1,"height":1},"opacity":1,"edgeAntialiasingMask":251658240,"height":1080,"hidden":false,"anchorPoint":{"pointX":0.5,"pointY":0.5}},"layers":[{"animations":[],"layers":[],"initialState":{"affineTransform":[1,0,0,1,0,0],"masksToBounds":false,"rotation":0,"scale":1,"position":{"pointX":960,"pointY":540},"width":1920,"sublayerTransform":[1,0,0,0,0,1,0,0,0,0,1,0,0,0,0,1],"contentsRect":{"y":0,"x":0,"width":1,"height":1},"opacity":1,"edgeAntialiasingMask":0,"height":1080,"hidden":false,"anchorPoint":{"pointX":0.5,"pointY":0.5}},"texture":"5BA6DF7ACEF516F7DAB78587CF30CE20"}]}]},{"animations":[],"initialState":{"affineTransform":[1,0,0,1,0,0],"masksToBounds":false,"rotation":0,"scale":1,"position":{"pointX":960,"pointY":540},"width":1920,"sublayerTransform":[1,0,0,0,0,1,0,0,0,0,1,0,0,0,0,1],"contentsRect":{"y":0,"x":0,"width":1,"height":1},"opacity":1,"edgeAntialiasingMask":251658240,"height":1080,"hidden":false,"anchorPoint":{"pointX":0.5,"pointY":0.5}},"layers":[{"animations":[],"initialState":{"affineTransform":[1,0,0,1,0,0],"masksToBounds":false,"rotation":0,"scale":1,"position":{"pointX":960.0000033378601,"pointY":228.658716917038},"width":1490.416235923767,"sublayerTransform":[1,0,0,0,0,1,0,0,0,0,1,0,0,0,0,1],"contentsRect":{"y":0,"x":0,"width":1,"height":1},"opacity":1,"edgeAntialiasingMask":251658240,"height":199.8542380332947,"hidden":false,"anchorPoint":{"pointX":0.5,"pointY":0.5}},"objectID":"66A29A77-91A6-459A-873B-2A720540AAE8","layers":[{"animations":[],"layers":[],"initialState":{"affineTransform":[1,0,0,1,0,0],"masksToBounds":false,"rotation":0,"scale":1,"position":{"pointX":749.2081146240234,"pointY":117.2684020996094},"width":804,"sublayerTransform":[1,0,0,0,0,1,0,0,0,0,1,0,0,0,0,1],"contentsRect":{"y":0,"x":0,"width":1,"height":1},"opacity":1,"edgeAntialiasingMask":0,"height":150,"hidden":false,"anchorPoint":{"pointX":0.5,"pointY":0.5}},"texture":"BC73DB09C2BE6F8E1AB988C55A0D508F"}]}]},{"animations":[],"initialState":{"affineTransform":[1,0,0,1,0,0],"masksToBounds":false,"rotation":0,"scale":1,"position":{"pointX":960,"pointY":540},"width":1920,"sublayerTransform":[1,0,0,0,0,1,0,0,0,0,1,0,0,0,0,1],"contentsRect":{"y":0,"x":0,"width":1,"height":1},"opacity":1,"edgeAntialiasingMask":251658240,"height":1080,"hidden":false,"anchorPoint":{"pointX":0.5,"pointY":0.5}},"layers":[{"animations":[],"initialState":{"affineTransform":[1,0,0,1,0,0],"masksToBounds":false,"rotation":0,"scale":1,"position":{"pointX":960,"pointY":658.5218505859375},"width":1008.924621582031,"sublayerTransform":[1,0,0,0,0,1,0,0,0,0,1,0,0,0,0,1],"contentsRect":{"y":0,"x":0,"width":1,"height":1},"opacity":1,"edgeAntialiasingMask":251658240,"height":573.0691528320312,"hidden":false,"anchorPoint":{"pointX":0.5,"pointY":0.5}},"objectID":"02FC3272-4CF6-46E2-9883-36AFEF6E092B","layers":[{"animations":[],"layers":[],"initialState":{"affineTransform":[1,0,0,1,0,0],"masksToBounds":false,"rotation":0,"scale":1,"position":{"pointX":504.4623107910156,"pointY":286.5127258300781},"width":1012,"sublayerTransform":[1,0,0,0,0,1,0,0,0,0,1,0,0,0,0,1],"contentsRect":{"y":0,"x":0,"width":1,"height":1},"opacity":1,"edgeAntialiasingMask":0,"height":577,"hidden":false,"anchorPoint":{"pointX":0.5,"pointY":0.5}},"texture":"404D9F46CAD725E5CB6CF5313B387FE7"}]}]}]}},{"effects":[{"beginTime":0,"baseLayer":{"animations":[],"initialState":{"affineTransform":[1,0,0,1,0,0],"masksToBounds":false,"rotation":0,"scale":1,"position":{"pointX":960,"pointY":540},"width":1920,"sublayerTransform":[1,0,0,0,0,1,0,0,0,0,1,0,0,0,0,1],"contentsRect":{"y":0,"x":0,"width":1,"height":1},"opacity":1,"edgeAntialiasingMask":251658240,"height":1080,"hidden":false,"anchorPoint":{"pointX":0.5,"pointY":0.5}},"objectID":"0","layers":[{"animations":[],"initialState":{"affineTransform":[1,0,0,1,0,0],"masksToBounds":false,"rotation":0,"scale":1,"position":{"pointX":960,"pointY":540},"width":1920,"sublayerTransform":[1,0,0,0,0,1,0,0,0,0,1,-0.0003500791246677598,0,0,0,1],"contentsRect":{"y":0,"x":0,"width":1,"height":1},"opacity":1,"edgeAntialiasingMask":251658240,"height":1080,"hidden":false,"anchorPoint":{"pointX":0.5,"pointY":0.5}},"layers":[{"animations":[],"layers":[],"initialState":{"affineTransform":[1,0,0,1,0,0],"masksToBounds":false,"rotation":0,"scale":1,"position":{"pointX":960,"pointY":540},"width":1920,"sublayerTransform":[1,0,0,0,0,1,0,0,0,0,1,0,0,0,0,1],"contentsRect":{"y":0,"x":0,"width":1,"height":1},"opacity":1,"edgeAntialiasingMask":0,"height":1080,"hidden":false,"anchorPoint":{"pointX":0.5,"pointY":0.5}},"texture":"F9D67537335693395CBA785731CD3476"},{"animations":[{"timeOffset":0,"from":{"scalar":false},"beginTime":0,"repeatCount":0,"fillMode":"both","property":"hidden","autoreverses":false,"duration":0.01,"to":{"scalar":true}}],"layers":[],"initialState":{"affineTransform":[1,0,0,1,0,0],"masksToBounds":false,"rotation":0,"scale":1,"position":{"pointX":960,"pointY":540},"width":1920,"sublayerTransform":[1,0,0,0,0,1,0,0,0,0,1,0,0,0,0,1],"contentsRect":{"y":0,"x":0,"width":1,"height":1},"opacity":1,"edgeAntialiasingMask":0,"height":1080,"hidden":false,"anchorPoint":{"pointX":0.5,"pointY":0.5}},"texture":"FD41AC253A9043B533BAC166837C08A6"}]}]},"effects":[],"duration":0.01,"type":"transition","name":"none","objectID":"0"}],"automaticPlay":false,"hyperlinks":[],"accessibility":[{"text":"ECMAScript","targetRectangle":{"y":134.9503479003906,"x":553.920015258789,"width":812.16,"height":189.35888671875}}],"baseLayer":{"animations":[],"initialState":{"affineTransform":[1,0,0,1,0,0],"masksToBounds":false,"rotation":0,"scale":1,"position":{"pointX":960,"pointY":540},"width":1920,"sublayerTransform":[1,0,0,0,0,1,0,0,0,0,1,0,0,0,0,1],"contentsRect":{"y":0,"x":0,"width":1,"height":1},"opacity":1,"edgeAntialiasingMask":251658240,"height":1080,"hidden":false,"anchorPoint":{"pointX":0.5,"pointY":0.5}},"objectID":"0","layers":[{"animations":[],"initialState":{"affineTransform":[1,0,0,1,0,0],"masksToBounds":false,"rotation":0,"scale":1,"position":{"pointX":960,"pointY":540},"width":1920,"sublayerTransform":[1,0,0,0,0,1,0,0,0,0,1,-0.0003500791246677598,0,0,0,1],"contentsRect":{"y":0,"x":0,"width":1,"height":1},"opacity":1,"edgeAntialiasingMask":251658240,"height":1080,"hidden":false,"anchorPoint":{"pointX":0.5,"pointY":0.5}},"layers":[{"animations":[],"layers":[],"initialState":{"affineTransform":[1,0,0,1,0,0],"masksToBounds":false,"rotation":0,"scale":1,"position":{"pointX":960,"pointY":540},"width":1920,"sublayerTransform":[1,0,0,0,0,1,0,0,0,0,1,0,0,0,0,1],"contentsRect":{"y":0,"x":0,"width":1,"height":1},"opacity":1,"edgeAntialiasingMask":0,"height":1080,"hidden":false,"anchorPoint":{"pointX":0.5,"pointY":0.5}},"texture":"FD41AC253A9043B533BAC166837C08A6"}]}]}}]}